{"v":5,"entries":{"atoms-button--primary":{"type":"story","id":"atoms-button--primary","name":"Primary","title":"Atoms/Button","importPath":"./src/components/Button/Button.stories.jsx","componentPath":"./src/components/Button/Button.jsx","tags":["dev","test","autodocs"]},"atoms-message--info":{"type":"story","id":"atoms-message--info","name":"Info","title":"Atoms/Message","importPath":"./src/components/Message/Message.stories.jsx","componentPath":"./src/components/Message/Message.jsx","tags":["dev","test","autodocs"]},"atoms-message--success":{"type":"story","id":"atoms-message--success","name":"Success","title":"Atoms/Message","importPath":"./src/components/Message/Message.stories.jsx","componentPath":"./src/components/Message/Message.jsx","tags":["dev","test","autodocs"]},"atoms-message--warning":{"type":"story","id":"atoms-message--warning","name":"Warning","title":"Atoms/Message","importPath":"./src/components/Message/Message.stories.jsx","componentPath":"./src/components/Message/Message.jsx","tags":["dev","test","autodocs"]},"atoms-message--error":{"type":"story","id":"atoms-message--error","name":"Error","title":"Atoms/Message","importPath":"./src/components/Message/Message.stories.jsx","componentPath":"./src/components/Message/Message.jsx","tags":["dev","test","autodocs"]}}}